microAgents/__init__.py
microAgents/core/__init__.py
microAgents/core/core.py
microAgents/core/message_store.py
microAgents/llm/__init__.py
microAgents/llm/llm.py
microAgents/llm/prompt.py
microagents-1.3.6.dist-info/METADATA
microagents-1.3.6.dist-info/WHEEL
microagents-1.3.6.dist-info/top_level.txt
microagents-1.3.6.dist-info/RECORD
