Metadata-Version: 2.4
Name: microAgents
Version: 1.3.6
Summary: A lightweight LLM orchestration framework for building Multi-Agent AI systems.
Home-page: https://github.com/prabhjots664/MicroAgents
Author: MicroAgents Team
Author-email: prabhjots664@gmail.com
Classifier: Programming Language :: Python :: 3
Classifier: License :: OSI Approved :: MIT License
Classifier: Operating System :: OS Independent
Classifier: Development Status :: 3 - Alpha
Classifier: Intended Audience :: Developers
Classifier: Topic :: Software Development :: Libraries :: Python Modules
Classifier: Topic :: Scientific/Engineering :: Artificial Intelligence
Requires-Python: >=3.6
Requires-Dist: requests>=2.25.0
Requires-Dist: urllib3>=1.26.0
Dynamic: author
Dynamic: author-email
Dynamic: classifier
Dynamic: description
Dynamic: description-content-type
Dynamic: home-page
Dynamic: requires-dist
Dynamic: requires-python
Dynamic: summary
